<?xml version="1.0" encoding="UTF-8"?>

<TC_LB_OperationManagement_EquipmentReceiptMade>
	<issueWaybill>
		<userName>admin</userName>
		<password>ne88888888</password>
		<useWpoint>西安城西</useWpoint>
		<issueAmount>1</issueAmount>
		<accepter>李易峰</accepter>
		<remark>ForAutoTest</remark>
	</issueWaybill>
	
	<sendWpointRecordWaybill>
		<userName>02930088</userName>
		<password>ne888888</password>
		<sendStatus>录单：西安城西</sendStatus>
	</sendWpointRecordWaybill>
	
	<sendWpointSendScan>
		<userName>02930088</userName>
		<password>ne888888</password>
		<transferStatus>发件：西安城西</transferStatus>
	</sendWpointSendScan>
	
	<wpointEquipmentReceiptMade>
		<userName>02930088</userName>
		<password>ne888888</password>
		<nextPoint>西安分拨中心</nextPoint>
	</wpointEquipmentReceiptMade>
	
	<wpointEquipmentReceiptManage>
		<userName>02930088</userName>
		<password>ne888888</password>
	</wpointEquipmentReceiptManage>
	
	<firstDistributionCenterInboundConfirm>
		<userName>07472</userName>
		<password>ne888888</password>
	</firstDistributionCenterInboundConfirm>
	
	<initializeWeight>
		<userName>07472</userName>
		<password>ne888888</password>
		<operatorName>张勇</operatorName>
	</initializeWeight>
	
	<operateGoodsAmountAssign>
		<userName>07472</userName>
		<password>ne888888</password>
		<belongsToTeamName>装卸一队</belongsToTeamName>
		<belongsToGroupName>装卸一组</belongsToGroupName>
		<operaterName1>张勇</operaterName1>
		<operaterName2>刘东</operaterName2>
	</operateGoodsAmountAssign>
	
	<operateGoodsAmountQuery>
		<userName>07472</userName>
		<password>ne888888</password>
		<operatorName>张勇</operatorName>
	</operateGoodsAmountQuery>
	
	<firstDistributionInboundWarehouseHandle>
		<userName>07472</userName>
		<password>ne888888</password>
	</firstDistributionInboundWarehouseHandle>
	
	<firstDistributionCenterFormalEquipmentReceiptMade>
		<userName>07472</userName>
		<password>ne888888</password>
		<nextWpoint>广州分拨中心</nextWpoint>
		<carNo>沪A34564</carNo>
	</firstDistributionCenterFormalEquipmentReceiptMade>
	
	<firstDistributionCenterEquipmentReceiptManage>
		<userName>07472</userName>
		<password>ne888888</password>
	</firstDistributionCenterEquipmentReceiptManage>
	
	<operateGoodsAmountAssign1>
		<userName>07472</userName>
		<password>ne888888</password>
		<belongsToTeamName>装卸一队</belongsToTeamName>
		<belongsToGroupName>装卸一组</belongsToGroupName>
		<operaterName1>张勇</operaterName1>
		<operaterName2>刘东</operaterName2>
	</operateGoodsAmountAssign1>
	
	<operateGoodsAmountQuery1>
		<userName>07472</userName>
		<password>ne888888</password>
		<operatorName>张勇</operatorName>
	</operateGoodsAmountQuery1>
	
	<firstDistributionSendScan>
		<userName>02930088</userName>
		<password>ne888888</password>
		<transferStatus>发件：西安分拨中心</transferStatus>
	</firstDistributionSendScan>
	
	<targetDistributionCenterInboundConfirm>
		<userName>11088</userName>
		<password>ne888888</password>
	</targetDistributionCenterInboundConfirm>
	
	<targetDistributionInboundWarehouseHandle>
		<userName>11088</userName>
		<password>ne888888</password>
	</targetDistributionInboundWarehouseHandle>
	
	<targetDistributionCenterFormalEquipmentReceiptMade>
		<userName>11088</userName>
		<password>ne888888</password>
		<nextWpoint>广州海珠</nextWpoint>
		<carNo>沪A34564</carNo>
	</targetDistributionCenterFormalEquipmentReceiptMade>
	
	<targetDistributionSendScan>
		<userName>02930088</userName>
		<password>ne888888</password>
		<transferStatus>发件：广州分拨中心</transferStatus>
	</targetDistributionSendScan>
	
	<targetWpointRecieveScan>
		<userName>02930088</userName>
		<password>ne888888</password>
		<transferStatus>到件：广州海珠</transferStatus>
	</targetWpointRecieveScan>
	
	<targetWpointDeliverScan>
		<userName>02930088</userName>
		<password>ne888888</password>
		<deliveryStatus>派件：广州海珠</deliveryStatus>
	</targetWpointDeliverScan>
	
	<targetWpointSignScan>
		<userName>02930088</userName>
		<password>ne888888</password>
		<signStatus>广州海珠</signStatus>
	</targetWpointSignScan>
	
</TC_LB_OperationManagement_EquipmentReceiptMade>